MomentumPyClient/__init__.py
MomentumPyClient/ui.py
MomentumPyClient/ws.py
momentumpyclient-0.0.5.dist-info/licenses/AUTHORS.rst
momentumpyclient-0.0.5.dist-info/licenses/LICENSE
momentumpyclient-0.0.5.dist-info/METADATA
momentumpyclient-0.0.5.dist-info/WHEEL
momentumpyclient-0.0.5.dist-info/top_level.txt
momentumpyclient-0.0.5.dist-info/RECORD
