Metadata-Version: 2.4
Name: MomentumPyClient
Version: 0.0.5
Summary: Python package for connection to Web Services of Momentum Scheduler (Thermo Scientific)
Author-email: Jesper Marino <jsqp@novonordisk.com>, Erik Trygg <etrg@novonordisk.com>
Classifier: Development Status :: 3 - Alpha
Classifier: Programming Language :: Python :: 3
Classifier: License :: OSI Approved :: MIT License
Classifier: Operating System :: OS Independent
Requires-Python: >=3.10
License-File: LICENSE
License-File: AUTHORS.rst
Requires-Dist: requests
Requires-Dist: python-dotenv
Provides-Extra: dev
Requires-Dist: pytest>8.3.3; extra == "dev"
Provides-Extra: streamlit
Requires-Dist: streamlit; extra == "streamlit"
Requires-Dist: plotly; extra == "streamlit"
Requires-Dist: pandas; extra == "streamlit"
Dynamic: license-file
